poglink/__init__.py
poglink/bot.py
poglink/config.py
poglink/error.py
poglink/main.py
poglink/utils.py
poglink/cogs/__init__.py
poglink/cogs/bans.py
poglink/cogs/rates.py
poglink/cogs/test.py
poglink/models/__init__.py
poglink/models/bans.py
poglink/models/rates.py
poglink-0.11.2.dist-info/LICENSE
poglink-0.11.2.dist-info/METADATA
poglink-0.11.2.dist-info/WHEEL
poglink-0.11.2.dist-info/entry_points.txt
poglink-0.11.2.dist-info/top_level.txt
poglink-0.11.2.dist-info/RECORD
