Metadata-Version: 2.1
Name: poglink
Version: 0.11.2
Summary: A bot that integrates the ARK Web API with Discord.
Home-page: https://github.com/FM-17/poglink,
Author: FM-17
Author-email: info@fm17.dev,
License: MIT
Project-URL: Bug Tracker, https://github.com/fm-17/poglink/issues
Project-URL: DockerHub, https://hub.docker.com/r/fm17/poglink
Classifier: Development Status :: 4 - Beta
Classifier: License :: OSI Approved :: MIT License
Classifier: Operating System :: POSIX :: Linux
Classifier: Programming Language :: Python :: 3.7
Classifier: Framework :: AsyncIO
Requires-Python: >=3.7
License-File: LICENSE
Requires-Dist: discord >=1.7
Requires-Dist: pyyaml
Requires-Dist: python-dateutil
Requires-Dist: jinja2
Requires-Dist: importlib-metadata
